odoo/addons/animal_owner/README.rst
odoo/addons/animal_owner/__init__.py
odoo/addons/animal_owner/__manifest__.py
odoo/addons/animal_owner/i18n/animal_owner.pot
odoo/addons/animal_owner/i18n/es.po
odoo/addons/animal_owner/models/__init__.py
odoo/addons/animal_owner/models/animal.py
odoo/addons/animal_owner/models/res_partner.py
odoo/addons/animal_owner/readme/CONTRIBUTORS.rst
odoo/addons/animal_owner/readme/DESCRIPTION.rst
odoo/addons/animal_owner/readme/USAGE.rst
odoo/addons/animal_owner/static/description/icon.png
odoo/addons/animal_owner/static/description/index.html
odoo/addons/animal_owner/views/animal.xml
odoo/addons/animal_owner/views/res_partner.xml
odoo12_addon_animal_owner-12.0.1.0.0.99.dev6.dist-info/METADATA
odoo12_addon_animal_owner-12.0.1.0.0.99.dev6.dist-info/WHEEL
odoo12_addon_animal_owner-12.0.1.0.0.99.dev6.dist-info/top_level.txt
odoo12_addon_animal_owner-12.0.1.0.0.99.dev6.dist-info/RECORD
